teqniqly/__init__.py
teqniqly/lahman_datasets.py
tq_lahman_datasets-1.0.dist-info/LICENSE
tq_lahman_datasets-1.0.dist-info/METADATA
tq_lahman_datasets-1.0.dist-info/WHEEL
tq_lahman_datasets-1.0.dist-info/top_level.txt
tq_lahman_datasets-1.0.dist-info/RECORD
