Metadata-Version: 2.1
Name: tq-lahman-datasets
Version: 1.0
Summary: This package contains the Lahman baseball database.
Home-page: https://github.com/farooq-teqniqly/tq-lahman-datasets
Author: Teqniqly
Author-email: farooq@teqniqly.com
License: MIT
Project-URL: GitHub, https://github.com/farooq-teqniqly/tq-lahman-datasets
Platform: UNKNOWN
Classifier: Development Status :: 5 - Production/Stable
Classifier: Programming Language :: Python
Classifier: Programming Language :: Python :: 3 :: Only
Classifier: Intended Audience :: Developers
Classifier: License :: OSI Approved :: MIT License
Classifier: Topic :: Software Development :: Libraries :: Python Modules
Classifier: Topic :: Database
Requires-Python: >=3.9
License-File: LICENSE
Requires-Dist: pandas
Requires-Dist: requests
Requires-Dist: tqdm
